hestia_earth/distribution/__init__.py
hestia_earth/distribution/cycle.py
hestia_earth/distribution/likelihood.py
hestia_earth/distribution/log.py
hestia_earth/distribution/posterior_fert.py
hestia_earth/distribution/posterior_irrigation.py
hestia_earth/distribution/posterior_pest.py
hestia_earth/distribution/posterior_yield.py
hestia_earth/distribution/prior_fert.py
hestia_earth/distribution/prior_irrigation.py
hestia_earth/distribution/prior_pest.py
hestia_earth/distribution/prior_yield.py
hestia_earth/distribution/version.py
hestia_earth/distribution/utils/MCMC_mv.py
hestia_earth/distribution/utils/__init__.py
hestia_earth/distribution/utils/csv.py
hestia_earth/distribution/utils/cycle.py
hestia_earth/distribution/utils/fao.py
hestia_earth/distribution/utils/posterior.py
hestia_earth/distribution/utils/priors.py
hestia_earth/distribution/utils/property.py
hestia_earth/distribution/utils/storage/__init__.py
hestia_earth/distribution/utils/storage/_azure_client.py
hestia_earth/distribution/utils/storage/_local_client.py
hestia_earth/distribution/utils/storage/_s3_client.py
hestia_earth_distribution-0.3.1.dist-info/licenses/LICENSE
hestia_earth_distribution-0.3.1.dist-info/METADATA
hestia_earth_distribution-0.3.1.dist-info/WHEEL
hestia_earth_distribution-0.3.1.dist-info/top_level.txt
hestia_earth_distribution-0.3.1.dist-info/RECORD
