Metadata-Version: 2.4
Name: hestia_earth_distribution
Version: 0.3.1
Summary: Hestia's Distribution library
Home-page: https://gitlab.com/hestia-earth/hestia-distribution
Author: Hestia Team
Author-email: guillaume@hestia.earth
License: MIT
Classifier: Programming Language :: Python :: 3.12
Requires-Python: >=3.12
License-File: LICENSE
Requires-Dist: hestia-earth-schema>=35.0.1
Requires-Dist: hestia-earth-utils>=0.16.7
Provides-Extra: stats
Requires-Dist: pymc; extra == "stats"
Requires-Dist: scipy; extra == "stats"
Provides-Extra: plotting
Requires-Dist: arviz; extra == "plotting"
Dynamic: author
Dynamic: author-email
Dynamic: classifier
Dynamic: description
Dynamic: description-content-type
Dynamic: home-page
Dynamic: license
Dynamic: license-file
Dynamic: provides-extra
Dynamic: requires-dist
Dynamic: requires-python
Dynamic: summary
